setup.py
quizzes/__init__.py
quizzes/fill.py
quizzes/questions.py
quizzes.egg-info/PKG-INFO
quizzes.egg-info/SOURCES.txt
quizzes.egg-info/dependency_links.txt
quizzes.egg-info/requires.txt
quizzes.egg-info/top_level.txt