Metadata-Version: 1.0
Name: quizzes
Version: 0.4
Summary: package to generate MCQ questions with options and answer
Home-page: UNKNOWN
Author: Vaibhav Agrawal
Author-email: UNKNOWN
License: UNKNOWN
Platform: UNKNOWN
